MANIFEST.in
README.rst
setup.py
django_quickblocks/__init__.py
django_quickblocks/admin.py
django_quickblocks/models.py
django_quickblocks/tests.py
django_quickblocks/urls.py
django_quickblocks/views.py
django_quickblocks.egg-info/PKG-INFO
django_quickblocks.egg-info/SOURCES.txt
django_quickblocks.egg-info/dependency_links.txt
django_quickblocks.egg-info/not-zip-safe
django_quickblocks.egg-info/requires.txt
django_quickblocks.egg-info/top_level.txt
django_quickblocks/templatetags/__init__.py
django_quickblocks/templatetags/quickblocks.py