Metadata-Version: 1.0
Name: django-quickblocks
Version: 0.9.1
Summary: UNKNOWN
Home-page: http://www.nyaruka.com/#open
Author: Nicolas Pottier, Eugene Rwagasore
Author-email: code@nyaruka.com
License: BSD
Download-URL: http://github.com/nyaruka/django-quickblocks
Platform: UNKNOWN
Classifier: Development Status :: 4 - Beta
Classifier: Environment :: Web Environment
Classifier: Intended Audience :: Developers
Classifier: License :: OSI Approved :: BSD License
Classifier: Operating System :: OS Independent
Classifier: Programming Language :: Python
Classifier: Framework :: Django
